{
  "post_id": "325670187920349_1312150404259776",
  "product": {
    "source": "amazon",
    "url": "https://www.amazon.com/gp/product/B0CZ7TQ1F8",
    "grit": 240,
    "pack": 10,
    "anchor": "240 Grit (Medium)",
    "grit_description": "Light refinement grit that blends sanding marks and smooths primer layers. Perfect for wood, resin, or plastic before lacquer application. Produces consistent scratch patterns and controlled results when used wet or dry.",
    "contexts": [
      "finishing"
    ]
  }
}