{
  "post_id": "325670187920349_1307089444765872",
  "product": {
    "source": "amazon",
    "url": "https://www.amazon.com/gp/product/B0CZ8DFS6T",
    "grit": 220,
    "pack": 10,
    "anchor": "220 Grit (Medium)",
    "grit_description": "Fine finishing grit for final surface preparation before painting or coating. Offers uniform cutting on wood, metal, and plastic. Leaves a smooth, paint-ready finish suitable for wet or dry sanding.",
    "contexts": [
      "wood",
      "metal",
      "auto",
      "drywall"
    ]
  }
}